{"run_number": "1597740617715483", "step_name": "compute_stats", "task_id": "19", "attempt_id": 0, "name": "name", "content_type": "gzip+pickle-v2", "type": "metaflow.artifact", "sha": "37d876fec9ea301c3177110bade9ba3f53b34307", "ds_type": "local", "location": "/Users/mdancho/Desktop/learning_labs/lab_41_metaflow/.metaflow/MovieStatsFlow/data/37/37d876fec9ea301c3177110bade9ba3f53b34307", "flow_id": "MovieStatsFlow", "user_name": "mdancho", "tags": [], "system_tags": ["user:mdancho", "runtime:dev", "python_version:3.6.11", "date:2020-08-18", "metaflow_version:2.2.0", "metaflow_r_version:2.2.0", "r_version:4.0.2"], "ts_epoch": 1597740632895}